[
  [
    "【深夜枠】おつかれさま会しよ､､､☆彡【ホロライブ/さくらみこ】",
    "EFIIbYiYmJ4",
    {
      "song_name": "glow(Acoustic Guitar Ver.)",
      "artist_name": "keeno",
      "start": "2265",
      "end": "2548"
    },
    {
      "song_name": "小夜子(Acoustic Guitar Ver.)",
      "artist_name": "みきとP",
      "start": "2569",
      "end": "2846"
    },
    {
      "song_name": "サマータイムレコード(Piano Ver.)",
      "artist_name": "じん",
      "start": "2913",
      "end": "3178"
    },
    {
      "song_name": "アヤノの幸福理論(Piano Ver.)",
      "artist_name": "じん",
      "start": "3207",
      "end": "3535"
    },
    {
      "song_name": "恋愛サーキュレーション",
      "artist_name": "千石撫子(CV:花澤香菜)",
      "start": "3745",
      "end": "3998"
    },
    {
      "song_name": "ハッピーシンセサイザ",
      "artist_name": "Easy Pop",
      "start": "4040",
      "end": "4383"
    },
    {
      "song_name": "お願いマッスル",
      "artist_name": "紗倉ひびき(CV:ファイルーズあい)＆街雄鳴造(CV:石川界人)",
      "start": "4561",
      "end": "4658"
    },
    {
      "song_name": "紅蓮華",
      "artist_name": "LiSA",
      "start": "4683",
      "end": "4916"
    },
    {
      "song_name": "名前のない怪物",
      "artist_name": "EGOIST",
      "start": "4955",
      "end": "5261"
    },
    {
      "song_name": "Departures ～あなたにおくるアイの歌～",
      "artist_name": "EGOIST",
      "start": "5348",
      "end": "5593"
    },
    {
      "song_name": "優しさの理由",
      "artist_name": "ChouCho",
      "start": "5605",
      "end": "5853"
    },
    {
      "song_name": "らしさ",
      "artist_name": "SUPER BEAVER",
      "start": "5880",
      "end": "6134"
    }
  ],
  [
    "【おはよ｡】朝活☀てきちょ～にうたう配信｡【ホロライブ/さくらみこ】",
    "ijVinWaZYhk",
    {
      "song_name": "キセキ",
      "artist_name": "GReeeeN",
      "start": "519",
      "end": "789"
    },
    {
      "song_name": "睡蓮花",
      "artist_name": "湘南乃風",
      "start": "1012",
      "end": "1443"
    },
    {
      "song_name": "ずっと ChamJam",
      "artist_name": "ChamJam",
      "start": "1597",
      "end": "1748"
    },
    {
      "song_name": "プラチナ",
      "artist_name": "坂本真綾",
      "start": "1974",
      "end": "2220"
    },
    {
      "song_name": "CLEAR",
      "artist_name": "坂本真綾",
      "start": "2237",
      "end": "2484"
    },
    {
      "song_name": "irony",
      "artist_name": "ClariS",
      "start": "2534",
      "end": "2790"
    },
    {
      "song_name": "ヒトリゴト",
      "artist_name": "ClariS",
      "start": "2807",
      "end": "3039"
    },
    {
      "song_name": "春擬き",
      "artist_name": "やなぎなぎ",
      "start": "3355",
      "end": "3618"
    },
    {
      "song_name": "Q&A リサイタル！",
      "artist_name": "戸松遥",
      "start": "3645",
      "end": "3739"
    },
    {
      "song_name": "檄！帝国華撃団",
      "artist_name": "帝国華撃団",
      "start": "3821",
      "end": "3998"
    },
    {
      "song_name": "コネクト",
      "artist_name": "ClariS",
      "start": "4083",
      "end": "4350"
    },
    {
      "song_name": "Baby Sweet Berry Love",
      "artist_name": "小倉唯",
      "start": "4457",
      "end": "4676"
    },
    {
      "song_name": "Fantastic future",
      "artist_name": "田村ゆかり",
      "start": "4574",
      "end": "4675"
    },
    {
      "song_name": "Happy Girl",
      "artist_name": "喜多村英梨",
      "start": "4741",
      "end": "4841"
    },
    {
      "song_name": "Girlish Lover",
      "artist_name": "自らを演出する乙女の会",
      "start": "5066",
      "end": "5155"
    },
    {
      "song_name": "六兆年と一夜物語(Piano Arrange)",
      "artist_name": "kemu",
      "start": "5314",
      "end": "5623"
    },
    {
      "song_name": "独りんぼエンヴィー(Piano Arrange)",
      "artist_name": "koyori",
      "start": "5638",
      "end": "5903"
    },
    {
      "song_name": "アスノヨゾラ哨戒班",
      "artist_name": "Orangestar",
      "start": "6089",
      "end": "6262"
    },
    {
      "song_name": "天ノ弱",
      "artist_name": "164",
      "start": "6268",
      "end": "6460"
    },
    {
      "song_name": "恋愛裁判(Piano Arrange)",
      "artist_name": "40mP",
      "start": "6584",
      "end": "6839"
    },
    {
      "song_name": "ODDS&ENDS",
      "artist_name": "ryo",
      "start": "6934",
      "end": "7263"
    },
    {
      "song_name": "千本桜",
      "artist_name": "黒うさP",
      "start": "7385",
      "end": "7624"
    }
  ],
  [
    "【朝活】みこちのゆるゆる歌雑談🌱🐣【ホロライブ/さくらみこ】",
    "OZY5eB4zyLw",
    {
      "song_name": "ありがとう",
      "artist_name": "いきものがかり",
      "start": "3849",
      "end": "4200"
    },
    {
      "song_name": "君じゃなきゃダメみたい",
      "artist_name": "大石昌良",
      "start": "4309",
      "end": "4537"
    }
  ]
]
