[
  [
    "【深夜枠】おつかれさま会しよ､､､☆彡【ホロライブ/さくらみこ】",
    "EFIIbYiYmJ4",
    {
      "song_name": "glow(Acoustic Guitar Ver.)",
      "artist_name": "keeno",
      "start": "2265",
      "end": "2548"
    },
    {
      "song_name": "小夜子(Acoustic Guitar Ver.)",
      "artist_name": "みきとP",
      "start": "2569",
      "end": "2846"
    },
    {
      "song_name": "サマータイムレコード(Piano Ver.)",
      "artist_name": "じん",
      "start": "2913",
      "end": "3178"
    },
    {
      "song_name": "アヤノの幸福理論(Piano Ver.)",
      "artist_name": "じん",
      "start": "3207",
      "end": "3535"
    },
    {
      "song_name": "恋愛サーキュレーション",
      "artist_name": "千石撫子(CV:花澤香菜)",
      "start": "3745",
      "end": "3998"
    },
    {
      "song_name": "ハッピーシンセサイザ",
      "artist_name": "Easy Pop",
      "start": "4040",
      "end": "4383"
    },
    {
      "song_name": "お願いマッスル",
      "artist_name": "紗倉ひびき(CV:ファイルーズあい)＆街雄鳴造(CV:石川界人)",
      "start": "4561",
      "end": "4658"
    },
    {
      "song_name": "紅蓮華",
      "artist_name": "LiSA",
      "start": "4683",
      "end": "4916"
    },
    {
      "song_name": "名前のない怪物",
      "artist_name": "EGOIST",
      "start": "4955",
      "end": "5261"
    },
    {
      "song_name": "Departures ～あなたにおくるアイの歌～",
      "artist_name": "EGOIST",
      "start": "5348",
      "end": "5593"
    },
    {
      "song_name": "優しさの理由",
      "artist_name": "ChouCho",
      "start": "5605",
      "end": "5853"
    },
    {
      "song_name": "らしさ",
      "artist_name": "SUPER BEAVER",
      "start": "5880",
      "end": "6134"
    }
  ],
  [
    "【おはよ｡】朝活☀てきちょ～にうたう配信｡【ホロライブ/さくらみこ】",
    "ijVinWaZYhk",
    {
      "song_name": "キセキ",
      "artist_name": "GReeeeN",
      "start": "519",
      "end": "789"
    },
    {
      "song_name": "睡蓮花",
      "artist_name": "湘南乃風",
      "start": "1012",
      "end": "1443"
    },
    {
      "song_name": "ずっと ChamJam",
      "artist_name": "ChamJam",
      "start": "1597",
      "end": "1748"
    },
    {
      "song_name": "プラチナ",
      "artist_name": "坂本真綾",
      "start": "1974",
      "end": "2220"
    },
    {
      "song_name": "CLEAR",
      "artist_name": "坂本真綾",
      "start": "2237",
      "end": "2484"
    },
    {
      "song_name": "irony",
      "artist_name": "ClariS",
      "start": "2534",
      "end": "2790"
    },
    {
      "song_name": "ヒトリゴト",
      "artist_name": "ClariS",
      "start": "2807",
      "end": "3039"
    },
    {
      "song_name": "春擬き",
      "artist_name": "やなぎなぎ",
      "start": "3355",
      "end": "3618"
    },
    {
      "song_name": "Q&A リサイタル！",
      "artist_name": "戸松遥",
      "start": "3645",
      "end": "3739"
    },
    {
      "song_name": "檄！帝国華撃団",
      "artist_name": "帝国華撃団",
      "start": "3821",
      "end": "3998"
    },
    {
      "song_name": "コネクト",
      "artist_name": "ClariS",
      "start": "4083",
      "end": "4350"
    },
    {
      "song_name": "Baby Sweet Berry Love",
      "artist_name": "小倉唯",
      "start": "4457",
      "end": "4676"
    },
    {
      "song_name": "Fantastic future",
      "artist_name": "田村ゆかり",
      "start": "4574",
      "end": "4675"
    },
    {
      "song_name": "Happy Girl",
      "artist_name": "喜多村英梨",
      "start": "4741",
      "end": "4841"
    },
    {
      "song_name": "Girlish Lover",
      "artist_name": "自らを演出する乙女の会",
      "start": "5066",
      "end": "5155"
    },
    {
      "song_name": "六兆年と一夜物語(Piano Arrange)",
      "artist_name": "kemu",
      "start": "5314",
      "end": "5623"
    },
    {
      "song_name": "独りんぼエンヴィー(Piano Arrange)",
      "artist_name": "koyori",
      "start": "5638",
      "end": "5903"
    },
    {
      "song_name": "アスノヨゾラ哨戒班",
      "artist_name": "Orangestar",
      "start": "6089",
      "end": "6262"
    },
    {
      "song_name": "天ノ弱",
      "artist_name": "164",
      "start": "6268",
      "end": "6460"
    },
    {
      "song_name": "恋愛裁判(Piano Arrange)",
      "artist_name": "40mP",
      "start": "6584",
      "end": "6839"
    },
    {
      "song_name": "ODDS&ENDS",
      "artist_name": "ryo",
      "start": "6934",
      "end": "7263"
    },
    {
      "song_name": "千本桜",
      "artist_name": "黒うさP",
      "start": "7385",
      "end": "7624"
    }
  ],
  [
    "【朝活】みこちのゆるゆる歌雑談🌱🐣【ホロライブ/さくらみこ】",
    "OZY5eB4zyLw",
    {
      "song_name": "ありがとう",
      "artist_name": "いきものがかり",
      "start": "3849",
      "end": "4200"
    },
    {
      "song_name": "君じゃなきゃダメみたい",
      "artist_name": "大石昌良",
      "start": "4309",
      "end": "4537"
    },
    {
      "song_name": "光",
      "artist_name": "宇多田ヒカル",
      "start": "4921",
      "end": "5020"
    },
    {
      "song_name": "ケロッ!とマーチ",
      "artist_name": "アニメ『ケロロ軍曹』オープニング",
      "start": "5093",
      "end": "5280"
    },
    {
      "song_name": "モザイクロール",
      "artist_name": "DECO*27",
      "start": "5402",
      "end": "5581"
    },
    {
      "song_name": "おちゃめ機能(アカペラ)",
      "artist_name": "ラマーズP",
      "start": "5585",
      "end": "5621"
    },
    {
      "song_name": "シュガーソングとビターステップ",
      "artist_name": "UNISON SQUARE GARDEN",
      "start": "5832",
      "end": "6081"
    },
    {
      "song_name": "桃色片想い",
      "artist_name": "松浦亜弥",
      "start": "6165",
      "end": "6416"
    },
    {
      "song_name": "純恋歌(1人2役)",
      "artist_name": "湘南乃風",
      "start": "6625",
      "end": "6940"
    },
    {
      "song_name": "バンザイ～好きでよかった～",
      "artist_name": "ウルフルズ",
      "start": "7103",
      "end": "7379"
    },
    {
      "song_name": "世界はそれを愛と呼ぶんだぜ",
      "artist_name": "サンボマスター",
      "start": "7515",
      "end": "7818"
    }
  ],
  [
    "【ARK歌枠】検証！アベレーションの危険地帯《下層》で無事にLIVEをすることはできるのか？【ホロライブ/さくらみこ】",
    "R1aQBlhGhUw",
    {
      "song_name": "君の知らない物語",
      "artist_name": "supercell",
      "start": "387",
      "end": "729"
    },
    {
      "song_name": "ライオン",
      "artist_name": "シェリル・ノーム starring May'n,ランカ・リー＝中島愛",
      "start": "740",
      "end": "1036"
    },
    {
      "song_name": "God knows...",
      "artist_name": "涼宮ハルヒ(平野綾)",
      "start": "1054",
      "end": "1330"
    },
    {
      "song_name": "コネクト",
      "artist_name": "ClariS",
      "start": "1333",
      "end": "1600"
    },
    {
      "song_name": "新宝島",
      "artist_name": "サカナクション",
      "start": "1624",
      "end": "1924"
    },
    {
      "song_name": "白日",
      "artist_name": "King Gnu",
      "start": "1945",
      "end": "2215"
    },
    {
      "song_name": "残酷な天使のテーゼ",
      "artist_name": "高橋洋子",
      "start": "2286",
      "end": "2538"
    },
    {
      "song_name": "魂のルフラン",
      "artist_name": "高橋洋子",
      "start": "2558",
      "end": "2872"
    },
    {
      "song_name": "名前のない怪物",
      "artist_name": "EGOIST",
      "start": "2892",
      "end": "3192"
    },
    {
      "song_name": "ロキ",
      "artist_name": "みきとP",
      "start": "3212",
      "end": "3434"
    },
    {
      "song_name": "シャルル",
      "artist_name": "バルーン",
      "start": "3449",
      "end": "3681"
    },
    {
      "song_name": "創聖のアクエリオン",
      "artist_name": "AKINO from bless4",
      "start": "3716",
      "end": "3994"
    },
    {
      "song_name": "secret base 〜君がくれたもの〜",
      "artist_name": "ZONE",
      "start": "4009",
      "end": "4304"
    }
  ],
  [
    "サクラカゼ / さくらみこ【オリジナル曲】",
    "X9zw0QF12Kc",
    {
      "song_name": "サクラカゼ",
      "artist_name": "さくらみこ",
      "start": "0",
      "end": "230"
    }
  ],
  [
    "【晩酌歌枠】オタクが晩酌しながらまったり歌うらしい【ホロライブ/さくらみこ】",
    "ogsA11xyLho",
    {
      "song_name": "glow",
      "artist_name": "Keeno",
      "start": "509",
      "end": "802"
    },
    {
      "song_name": "海を泳ぐ月",
      "artist_name": "40mP",
      "start": "885",
      "end": "1152"
    },
    {
      "song_name": "寝・逃・げでリセット",
      "artist_name": "柊つかさ(福原香織) ",
      "start": "1250",
      "end": "1369"
    },
    {
      "song_name": "もってけ！セーラーふく",
      "artist_name": "泉こなた(平野綾)、柊かがみ(加藤英美里)、柊つかさ(福原香織)、高良みゆき(遠藤綾)",
      "start": "1398",
      "end": "1660"
    },
    {
      "song_name": "かくしん的☆めたまるふぉ～ぜっ!",
      "artist_name": "土間うまる(田中あいみ)",
      "start": "1779",
      "end": "1988"
    },
    {
      "song_name": "スキ? キライ!? スキ!!!",
      "artist_name": "ルイズ(釘宮理恵)",
      "start": "2338",
      "end": "2591"
    },
    {
      "song_name": "平行線",
      "artist_name": "酸欠少女さユり",
      "start": "2712",
      "end": "3011"
    },
    {
      "song_name": "アイマイモコ",
      "artist_name": "水瀬いのり",
      "start": "3403",
      "end": "3512"
    },
    {
      "song_name": "心拍数#0822",
      "artist_name": "蝶々P",
      "start": "3566",
      "end": "3852"
    },
    {
      "song_name": "天樂",
      "artist_name": "ゆうゆ",
      "start": "3858",
      "end": "4130"
    },
    {
      "song_name": "SPiCa",
      "artist_name": "toku",
      "start": "4139",
      "end": "4356"
    },
    {
      "song_name": "カタオモイ",
      "artist_name": "Aimer",
      "start": "4368",
      "end": "4575"
    },
    {
      "song_name": "Tulip",
      "artist_name": "LiPPS",
      "start": "4653",
      "end": "4880"
    },
    {
      "song_name": "五等分の気持ち",
      "artist_name": "中野家の五つ子",
      "start": "4949",
      "end": "5169"
    },
    {
      "song_name": "さよならメモリーズ",
      "artist_name": "supercell",
      "start": "5363",
      "end": "5729"
    },
    {
      "song_name": "凛として咲く花の如く",
      "artist_name": "紅色リトマス",
      "start": "5760",
      "end": "5853"
    },
    {
      "song_name": "凛として咲く花の如く(テイク2)",
      "artist_name": "紅色リトマス",
      "start": "5865",
      "end": "6096"
    },
    {
      "song_name": "白金ディスコ(吉幾三コール入り)",
      "artist_name": "阿良々木月火(井口裕香)",
      "start": "6443",
      "end": "6698"
    },
    {
      "song_name": "そばかす",
      "artist_name": "JUDY AND MARY",
      "start": "6860",
      "end": "7112"
    },
    {
      "song_name": "Rising Hope",
      "artist_name": "LiSA ",
      "start": "7243",
      "end": "7491"
    },
    {
      "song_name": "Preserved Roses",
      "artist_name": "T.M.Revolution×水樹奈々",
      "start": "7494",
      "end": "7700"
    },
    {
      "song_name": "革命デュアリズム",
      "artist_name": "水樹奈々×T.M.Revolution",
      "start": "7702",
      "end": "7940"
    },
    {
      "song_name": "ロキ",
      "artist_name": "みきとP",
      "start": "7990",
      "end": "8217"
    },
    {
      "song_name": "POP TEAM EPIC",
      "artist_name": "上坂すみれ",
      "start": "8222",
      "end": "8474"
    },
    {
      "song_name": "fancy baby doll（途中爆音注意）",
      "artist_name": "田村ゆかり",
      "start": "8933",
      "end": "9118"
    }
  ],
  [
    "【昼枠】ARK準備休憩がてらに歌います🎤【ホロライブ/さくらみこ】",
    "C7bEIxc5n90",
    {
      "song_name": "二息歩行",
      "artist_name": "DECO*27",
      "start": "823",
      "end": "1008"
    },
    {
      "song_name": "結ンデ開イテ羅刹ト骸",
      "artist_name": "ハチ",
      "start": "1082",
      "end": "1336"
    },
    {
      "song_name": "桃源郷エイリアン",
      "artist_name": "serial TV drama",
      "start": "1381",
      "end": "1682"
    },
    {
      "song_name": "ダダダダ天使",
      "artist_name": "ナナヲアカリ",
      "start": "1763",
      "end": "1980"
    },
    {
      "song_name": "ハナマル☆センセイション",
      "artist_name": "Little Non",
      "start": "2066",
      "end": "2292"
    },
    {
      "song_name": "だんご大家族",
      "artist_name": "『CLANNAD』より",
      "start": "2350",
      "end": "2629"
    },
    {
      "song_name": "パプリカ",
      "artist_name": "Foorin",
      "start": "2870",
      "end": "3057"
    },
    {
      "song_name": "地球最後の告白を",
      "artist_name": "kemu",
      "start": "3321",
      "end": "3575"
    },
    {
      "song_name": "ふわふわ時間",
      "artist_name": "放課後ティータイム",
      "start": "3718",
      "end": "3952"
    },
    {
      "song_name": "白日",
      "artist_name": "King Gnu",
      "start": "3992",
      "end": "4265"
    },
    {
      "song_name": "さよならメモリーズ",
      "artist_name": "supercell",
      "start": "4405",
      "end": "4768"
    },
    {
      "song_name": "桜",
      "artist_name": "コブクロ",
      "start": "5052",
      "end": "5206"
    },
    {
      "song_name": "SAKURAスキップ",
      "artist_name": "fourfolium",
      "start": "5310",
      "end": "5536"
    },
    {
      "song_name": "キラメキライダー☆",
      "artist_name": "hololive IDOL PROJECT",
      "start": "5587",
      "end": "5873"
    },
    {
      "song_name": "夢見る空へ",
      "artist_name": "hololive IDOL PROJECT",
      "start": "5900",
      "end": "6137"
    }
  ],
  [
    "",
    "",
    {
      "song_name": "",
      "artist_name": "",
      "start": "",
      "end": ""
    },
    {
      "song_name": "",
      "artist_name": "",
      "start": "",
      "end": ""
    },
    {
      "song_name": "",
      "artist_name": "",
      "start": "",
      "end": ""
    },
    {
      "song_name": "",
      "artist_name": "",
      "start": "",
      "end": ""
    },
    {
      "song_name": "",
      "artist_name": "",
      "start": "",
      "end": ""
    },
    {
      "song_name": "",
      "artist_name": "",
      "start": "",
      "end": ""
    }
  ]
]
